__init__.py
dtrelib.py
dtrelib-0.2.6.dist-info/LICENSE
dtrelib-0.2.6.dist-info/METADATA
dtrelib-0.2.6.dist-info/WHEEL
dtrelib-0.2.6.dist-info/top_level.txt
dtrelib-0.2.6.dist-info/RECORD
