Metadata-Version: 2.1
Name: dtrelib
Version: 0.2.6
Summary: Drive test report engine (DTRE) core library
Author-email: AlexTaran <at@dmtel.ru>
Project-URL: Homepage, https://pypi.org/project/dtrelib
Classifier: Programming Language :: Python :: 3
Classifier: License :: OSI Approved :: MIT License
Classifier: Operating System :: OS Independent
Requires-Python: >=3.7
License-File: LICENSE
